sdsaxsviewer/__init__.py
sdsaxsviewer/__main__.py
sdsaxsviewer/main.py
sdsaxsviewer-0.2.0.dist-info/licenses/LICENSE
sdsaxsviewer-0.2.0.dist-info/METADATA
sdsaxsviewer-0.2.0.dist-info/WHEEL
sdsaxsviewer-0.2.0.dist-info/entry_points.txt
sdsaxsviewer-0.2.0.dist-info/top_level.txt
sdsaxsviewer-0.2.0.dist-info/RECORD
