Metadata-Version: 2.4
Name: sdsaxsviewer
Version: 0.2.0
Summary: A graphical tool for visualizing SAXS data files
Author-email: Your Name <your.email@example.com>
License: MIT
Project-URL: Homepage, https://github.com/yourusername/sdsaxsviewer
Project-URL: Bug Tracker, https://github.com/yourusername/sdsaxsviewer/issues
Classifier: Programming Language :: Python :: 3
Classifier: License :: OSI Approved :: MIT License
Classifier: Operating System :: OS Independent
Classifier: Topic :: Scientific/Engineering :: Visualization
Classifier: Topic :: Scientific/Engineering :: Physics
Requires-Python: >=3.7
License-File: LICENSE
Requires-Dist: numpy
Requires-Dist: matplotlib
Requires-Dist: tifffile
Requires-Dist: fabio
Requires-Dist: PySide6
Dynamic: license-file
